dodgey/__init__.py
dodgey/_version.py
dodgey/core.py
dodgey/py.typed
dodgey/scanpy.py
dodgey/sparse.py
dodgey/stats.py
dodgey/typing.py
dodgey-0.1.0.dist-info/METADATA
dodgey-0.1.0.dist-info/WHEEL
dodgey-0.1.0.dist-info/licenses/LICENSE
dodgey-0.1.0.dist-info/RECORD
