Metadata-Version: 2.4
Name: dodgey
Version: 0.1.0
Summary: ROGUE-inspired cluster purity scoring for count matrices
Project-URL: Homepage, https://github.com/AxelMMalaghan/DODGEY
Project-URL: Source, https://github.com/AxelMMalaghan/DODGEY
Project-URL: Issues, https://github.com/AxelMMalaghan/DODGEY/issues
Author: Dodgey contributors
License: MIT License
License-File: LICENSE
Keywords: bioinformatics,clustering,quality-control,rogue,single-cell
Classifier: Development Status :: 3 - Alpha
Classifier: Intended Audience :: Science/Research
Classifier: License :: OSI Approved :: MIT License
Classifier: Programming Language :: Python :: 3
Classifier: Programming Language :: Python :: 3.10
Classifier: Programming Language :: Python :: 3.11
Classifier: Programming Language :: Python :: 3.12
Classifier: Programming Language :: Python :: 3.13
Classifier: Topic :: Scientific/Engineering :: Bio-Informatics
Requires-Python: >=3.10
Requires-Dist: numpy>=1.24
Requires-Dist: scipy>=1.10
Requires-Dist: statsmodels>=0.14
Provides-Extra: dev
Requires-Dist: mypy>=1.7; extra == 'dev'
Requires-Dist: pytest>=7.4; extra == 'dev'
Requires-Dist: ruff>=0.4; extra == 'dev'
Provides-Extra: scanpy
Requires-Dist: anndata>=0.10; extra == 'scanpy'
Requires-Dist: pandas>=2.0; extra == 'scanpy'
